mkdocs_coverage-2.0.0.dist-info/METADATA
mkdocs_coverage-2.0.0.dist-info/WHEEL
mkdocs_coverage-2.0.0.dist-info/entry_points.txt
mkdocs_coverage-2.0.0.dist-info/licenses/LICENSE
mkdocs_coverage/__init__.py
mkdocs_coverage/_internal/__init__.py
mkdocs_coverage/_internal/debug.py
mkdocs_coverage/_internal/plugin.py
mkdocs_coverage/py.typed
mkdocs_coverage-2.0.0.dist-info/RECORD
