Metadata-Version: 2.4
Name: mkdocs-coverage
Version: 2.0.0
Summary: MkDocs plugin to integrate your coverage HTML report into your site.
Author-Email: =?utf-8?q?Timoth=C3=A9e_Mazzucotelli?= <dev@pawamoy.fr>
License-Expression: ISC
License-File: LICENSE
Classifier: Development Status :: 4 - Beta
Classifier: Intended Audience :: Developers
Classifier: Programming Language :: Python
Classifier: Programming Language :: Python :: 3
Classifier: Programming Language :: Python :: 3 :: Only
Classifier: Programming Language :: Python :: 3.9
Classifier: Programming Language :: Python :: 3.10
Classifier: Programming Language :: Python :: 3.11
Classifier: Programming Language :: Python :: 3.12
Classifier: Programming Language :: Python :: 3.13
Classifier: Programming Language :: Python :: 3.14
Classifier: Topic :: Documentation
Classifier: Topic :: Software Development
Classifier: Topic :: Software Development :: Documentation
Classifier: Topic :: Utilities
Classifier: Typing :: Typed
Project-URL: Homepage, https://pawamoy.github.io/mkdocs-coverage
Project-URL: Documentation, https://pawamoy.github.io/mkdocs-coverage
Project-URL: Changelog, https://pawamoy.github.io/mkdocs-coverage/changelog
Project-URL: Repository, https://github.com/pawamoy/mkdocs-coverage
Project-URL: Issues, https://github.com/pawamoy/mkdocs-coverage/issues
Project-URL: Discussions, https://github.com/pawamoy/mkdocs-coverage/discussions
Project-URL: Gitter, https://gitter.im/mkdocs-coverage/community
Project-URL: Funding, https://github.com/sponsors/pawamoy
Requires-Python: >=3.9
Requires-Dist: mkdocs>=1.6
